dlhub_cli/__init__.py
dlhub_cli/config.py
dlhub_cli/main.py
dlhub_cli/printing.py
dlhub_cli/version.py
dlhub_cli/commands/__init__.py
dlhub_cli/commands/describe.py
dlhub_cli/commands/init.py
dlhub_cli/commands/login.py
dlhub_cli/commands/logout.py
dlhub_cli/commands/ls.py
dlhub_cli/commands/methods.py
dlhub_cli/commands/publish.py
dlhub_cli/commands/run.py
dlhub_cli/commands/search.py
dlhub_cli/commands/servables.py
dlhub_cli/commands/status.py
dlhub_cli/commands/update.py
dlhub_cli/commands/whoami.py
dlhub_cli/commands/init_templates/describe_servable.py.template
dlhub_cli/parsing/__init__.py
dlhub_cli/parsing/click_wrappers.py
dlhub_cli/parsing/main.py
dlhub_cli-0.6.1.dist-info/LICENSE
dlhub_cli-0.6.1.dist-info/METADATA
dlhub_cli-0.6.1.dist-info/WHEEL
dlhub_cli-0.6.1.dist-info/entry_points.txt
dlhub_cli-0.6.1.dist-info/top_level.txt
dlhub_cli-0.6.1.dist-info/RECORD
