Metadata-Version: 2.1
Name: dlhub-cli
Version: 0.6.1
Summary: DLHub CLI
Home-page: https://github.com/DLHub-Argonne/dlhub_cli
Author: Ryan Chard
Author-email: rchard@anl.gov
License: UNKNOWN
Keywords: DLHub,Data and Learning Hub for Science,machine learning,data publication,reproducibility
Platform: UNKNOWN
Classifier: Development Status :: 2 - Pre-Alpha
Classifier: Intended Audience :: Developers
Classifier: License :: OSI Approved :: Apache Software License
Classifier: Operating System :: POSIX
Classifier: Programming Language :: Python
Requires-Python: >=3.4
Requires-Dist: click (>=6.6)
Requires-Dist: requests (<3.0.0,>=2.0.0)
Requires-Dist: dlhub-sdk (>=0.6.0)
Requires-Dist: pyyaml (>=4.2b1)
Requires-Dist: tabulate
